LICENSE
MANIFEST.in
setup.py
testasposepdfcloud/__init__.py
testasposepdfcloud/api_client.py
testasposepdfcloud/configuration.py
testasposepdfcloud/rest.py
testasposepdfcloud.egg-info/PKG-INFO
testasposepdfcloud.egg-info/SOURCES.txt
testasposepdfcloud.egg-info/dependency_links.txt
testasposepdfcloud.egg-info/requires.txt
testasposepdfcloud.egg-info/top_level.txt
testasposepdfcloud/apis/__init__.py
testasposepdfcloud/apis/pdf_api.py
testasposepdfcloud/models/__init__.py
testasposepdfcloud/models/annotation.py
testasposepdfcloud/models/annotation_response.py
testasposepdfcloud/models/annotations.py
testasposepdfcloud/models/annotations_response.py
testasposepdfcloud/models/append_document.py
testasposepdfcloud/models/attachment.py
testasposepdfcloud/models/attachment_response.py
testasposepdfcloud/models/attachments.py
testasposepdfcloud/models/attachments_response.py
testasposepdfcloud/models/bookmarks.py
testasposepdfcloud/models/bookmarks_response.py
testasposepdfcloud/models/color.py
testasposepdfcloud/models/document.py
testasposepdfcloud/models/document_pages_response.py
testasposepdfcloud/models/document_properties.py
testasposepdfcloud/models/document_properties_response.py
testasposepdfcloud/models/document_property.py
testasposepdfcloud/models/document_property_response.py
testasposepdfcloud/models/document_response.py
testasposepdfcloud/models/document_text_replace_response.py
testasposepdfcloud/models/field.py
testasposepdfcloud/models/field_response.py
testasposepdfcloud/models/field_type.py
testasposepdfcloud/models/fields.py
testasposepdfcloud/models/fields_response.py
testasposepdfcloud/models/font_styles.py
testasposepdfcloud/models/horizontal_alignment.py
testasposepdfcloud/models/http_status_code.py
testasposepdfcloud/models/image.py
testasposepdfcloud/models/image_response.py
testasposepdfcloud/models/images.py
testasposepdfcloud/models/images_list_request.py
testasposepdfcloud/models/images_response.py
testasposepdfcloud/models/line_spacing.py
testasposepdfcloud/models/link.py
testasposepdfcloud/models/link_action_type.py
testasposepdfcloud/models/link_annotation.py
testasposepdfcloud/models/link_annotation_response.py
