Metadata-Version: 1.1
Name: testasposepdfcloud
Version: 1.0.15
Summary: Aspose.PDF for Cloud
Home-page: https://products.aspose.cloud/pdf/cloud
Author: Aspose PDF for Cloud
Author-email: UNKNOWN
License: MIT
Keywords: swagger,aspose,aspose cloud,pdf,sdk
Platform: UNKNOWN
Classifier: Development Status :: 5 - Production/Stable
Classifier: Intended Audience :: Developers
Classifier: Topic :: Software Development
Classifier: License :: OSI Approved :: MIT License
Classifier: Programming Language :: Python :: 2
Classifier: Programming Language :: Python :: 3
